pytket/extensions/qsharp/__init__.py
pytket/extensions/qsharp/_metadata.py
pytket/extensions/qsharp/py.typed
pytket/extensions/qsharp/qsharp_convert.py
pytket/extensions/qsharp/backends/__init__.py
pytket/extensions/qsharp/backends/azure_quantum.py
pytket/extensions/qsharp/backends/common.py
pytket/extensions/qsharp/backends/config.py
pytket/extensions/qsharp/backends/estimator.py
pytket/extensions/qsharp/backends/simulator.py
pytket/extensions/qsharp/backends/toffoli.py
pytket_qsharp-0.40.0.dist-info/LICENSE
pytket_qsharp-0.40.0.dist-info/METADATA
pytket_qsharp-0.40.0.dist-info/WHEEL
pytket_qsharp-0.40.0.dist-info/top_level.txt
pytket_qsharp-0.40.0.dist-info/RECORD
