Metadata-Version: 2.1
Name: pytket-qsharp
Version: 0.40.0
Summary: Extension for pytket, providing access to Azure devices and simulators via Microsoft QDK
Author: TKET development team
Author-email: tket-support@cambridgequantum.com
License: Apache 2
Project-URL: Documentation, https://cqcl.github.io/pytket-qsharp/api/index.html
Project-URL: Source, https://github.com/CQCL/pytket-qsharp
Project-URL: Tracker, https://github.com/CQCL/pytket-qsharp/issues
Classifier: Environment :: Console
Classifier: Programming Language :: Python :: 3.10
Classifier: Programming Language :: Python :: 3.11
Classifier: Programming Language :: Python :: 3.12
Classifier: License :: OSI Approved :: Apache Software License
Classifier: Operating System :: MacOS :: MacOS X
Classifier: Operating System :: POSIX :: Linux
Classifier: Operating System :: Microsoft :: Windows
Classifier: Intended Audience :: Developers
Classifier: Intended Audience :: Science/Research
Classifier: Topic :: Scientific/Engineering
Requires-Python: >=3.10
License-File: LICENSE
Requires-Dist: pytket ~=1.26
Requires-Dist: qsharp ~=0.28.291394
Requires-Dist: qsharp-core ~=0.28.291394
Requires-Dist: markdown
